{
  "_class": "shapeGroup",
  "clippingMaskMode": 0,
  "do_objectID": "C15B6539-BB84-40B6-81DB-AD4577135519",
  "exportOptions": {
    "_class": "exportOptions",
    "exportFormats": [
    ],
    "includedLayerIds": [
    ],
    "layerOptions": 0,
    "shouldTrim": false
  },
  "frame": {
    "_class": "rect",
    "constrainProportions": false,
    "height": 5.717333333333335,
    "width": 9.112,
    "x": 157.4053333333331,
    "y": 9.469333333333314
  },
  "hasClickThrough": false,
  "hasClippingMask": false,
  "isFlippedHorizontal": false,
  "isFlippedVertical": false,
  "isLocked": false,
  "isVisible": true,
  "layerListExpandedType": 0,
  "layers": [
    {
      "class": "shapePath",
      "id": "7E6159E3-0950-4EFA-9D29-683CD4E4C2E8"
    },
    {
      "class": "shapePath",
      "id": "1ED7C044-201F-47F0-BF93-CB0BDC524D6C"
    },
    {
      "class": "shapePath",
      "id": "5DB4DD5E-B687-4B41-A31F-3771AD31727F"
    },
    {
      "class": "shapePath",
      "id": "DE9012AA-0C39-4624-AE5D-50067EB43C93"
    }
  ],
  "name": "Cellular Connection",
  "nameIsFixed": true,
  "resizingConstraint": 12,
  "resizingType": 0,
  "rotation": 0,
  "shouldBreakMaskChain": false,
  "style": {
    "_class": "style",
    "blur": {
      "_class": "blur",
      "center": "{0.5, 0.5}",
      "isEnabled": false,
      "motionAngle": 0,
      "radius": 5.36,
      "type": 0
    },
    "endDecorationType": 0,
    "fills": [
      {
        "_class": "fill",
        "color": {
          "_class": "color",
          "alpha": 1,
          "blue": 0,
          "green": 0,
          "red": 0
        },
        "fillType": 0,
        "isEnabled": true,
        "noiseIndex": 0,
        "noiseIntensity": 0,
        "patternFillType": 1,
        "patternTileScale": 1
      }
    ],
    "miterLimit": 10,
    "startDecorationType": 0
  },
  "windingRule": 0
}